flaskbb_plugin_recent_topics-0.0.1.dist-info/METADATA
flaskbb_plugin_recent_topics-0.0.1.dist-info/RECORD
flaskbb_plugin_recent_topics-0.0.1.dist-info/WHEEL
flaskbb_plugin_recent_topics-0.0.1.dist-info/entry_points.txt
flaskbb_plugin_recent_topics-0.0.1.dist-info/top_level.txt
recent_topics/__init__.py
recent_topics/views.py
recent_topics/templates/recent_topics.html
recent_topics/templates/recent_topics_navlink.html
