Metadata-Version: 2.1
Name: flaskbb-plugin-recent-topics
Version: 0.0.1
Summary: Track unread topics.
Home-page: UNKNOWN
Author: Михаил Лебедев
Author-email: micha030201@gmail.com
License: BSD License
Keywords: flaskbb plugin
Platform: any
Classifier: Development Status :: 5 - Production/Stable
Classifier: Environment :: Web Environment
Classifier: Environment :: Plugins
Classifier: Framework :: Flask
Classifier: Intended Audience :: Developers
Classifier: License :: OSI Approved :: BSD License
Classifier: Operating System :: OS Independent
Classifier: Programming Language :: Python
Classifier: Programming Language :: Python :: 3
Classifier: Topic :: Internet :: WWW/HTTP :: Dynamic Content
Classifier: Topic :: Software Development :: Libraries :: Python Modules
Requires-Dist: FlaskBB
